pitchclock/__init__.py
pitchclock/__main__.py
pitchclock-0.0.4.dist-info/DESCRIPTION.rst
pitchclock-0.0.4.dist-info/METADATA
pitchclock-0.0.4.dist-info/RECORD
pitchclock-0.0.4.dist-info/WHEEL
pitchclock-0.0.4.dist-info/metadata.json
pitchclock-0.0.4.dist-info/top_level.txt
