Metadata-Version: 2.0
Name: pitchclock
Version: 0.0.4
Summary: Tone clock visualizations
Home-page: https://github.com/hosford42/pitchclock
Author: Aaron Hosford
Author-email: hosford42@gmail.com
License: MIT
Keywords: music musical tone clock visualization just intonation tonal atonal key signature scale chord
Platform: any
Classifier: Development Status :: 4 - Beta
Classifier: Intended Audience :: Developers
Classifier: Intended Audience :: Science/Research
Classifier: Intended Audience :: Other Audience
Classifier: License :: OSI Approved :: MIT License
Classifier: Operating System :: OS Independent
Classifier: Programming Language :: Python :: 3 :: Only
Classifier: Topic :: Artistic Software
Classifier: Topic :: Multimedia :: Graphics
Classifier: Topic :: Multimedia :: Sound/Audio :: Analysis
Classifier: Topic :: Scientific/Engineering :: Visualization
Requires-Dist: gizeh
